{
    "asset": {
        "format": "BMP",
        "id": "0075de7618ca016ad11178c4c4a862f9",
        "name": "img123456_399.BMP",
        "path": "file:/Users/chandanar/Desktop/FYP/kims_annotated/ulcers/img123456_399.BMP",
        "size": {
            "width": 352,
            "height": 288
        },
        "state": 2,
        "type": 1
    },
    "regions": [
        {
            "id": "yKx457vgN",
            "type": "RECTANGLE",
            "tags": [
                "ulcer"
            ],
            "boundingBox": {
                "height": 46.16102789256198,
                "width": 150.43871513102283,
                "left": 61.56117920540997,
                "top": 44.41774276859504
            },
            "points": [
                {
                    "x": 61.56117920540997,
                    "y": 44.41774276859504
                },
                {
                    "x": 211.9998943364328,
                    "y": 44.41774276859504
                },
                {
                    "x": 211.9998943364328,
                    "y": 90.57877066115702
                },
                {
                    "x": 61.56117920540997,
                    "y": 90.57877066115702
                }
            ]
        },
        {
            "id": "HPGfM7tkz",
            "type": "RECTANGLE",
            "tags": [
                "ulcer"
            ],
            "boundingBox": {
                "height": 100.19589359504133,
                "width": 27.86612426035503,
                "left": 260.03307269653425,
                "top": 111.7236570247934
            },
            "points": [
                {
                    "x": 260.03307269653425,
                    "y": 111.7236570247934
                },
                {
                    "x": 287.8991969568892,
                    "y": 111.7236570247934
                },
                {
                    "x": 287.8991969568892,
                    "y": 211.91955061983472
                },
                {
                    "x": 260.03307269653425,
                    "y": 211.91955061983472
                }
            ]
        }
    ],
    "version": "2.2.0"
}